biomagicbox/__init__.py
biomagicbox/expasy.py
biomagicbox-0.1.0.dist-info/LICENSE
biomagicbox-0.1.0.dist-info/METADATA
biomagicbox-0.1.0.dist-info/WHEEL
biomagicbox-0.1.0.dist-info/top_level.txt
biomagicbox-0.1.0.dist-info/RECORD
